taxteclib/__init__.py
taxteclib/database_logger.py
taxteclib/github_updater.py
taxteclib/playwright/__init__.py
taxteclib/playwright/afip.py
taxteclib/playwright/base.py
taxteclib/playwright/exceptions.py
taxteclib-0.3.2.dist-info/licenses/LICENSE
taxteclib-0.3.2.dist-info/METADATA
taxteclib-0.3.2.dist-info/WHEEL
taxteclib-0.3.2.dist-info/top_level.txt
taxteclib-0.3.2.dist-info/RECORD
