Metadata-Version: 2.4
Name: taxteclib
Version: 0.3.2
Summary: Libreria estandar para DeloitteAR BPS Tax Tech
Author-email: Leonel Marinaro <lmarinaro@deloitte.com>, Amiel Iriarte <amiriarte@deloitte.com>
License: MIT
Requires-Python: >=3.12
License-File: LICENSE
Requires-Dist: pyodbc>=5.2.0
Requires-Dist: python-dotenv>=1.1.1
Requires-Dist: requests>=2.32.5
Requires-Dist: sqlalchemy>=2.0.43
Requires-Dist: playwright>=1.48.0
Requires-Dist: pytest-asyncio>=1.2.0
Requires-Dist: urllib3>=2.5.0
Dynamic: license-file
